PyANSI/__init__.py
PyANSI/colors.py
PyANSI/colours.py
PyANSI/cursor.py
PyANSI/windows.py
PyANSI-1.2.0.dist-info/LICENSE
PyANSI-1.2.0.dist-info/METADATA
PyANSI-1.2.0.dist-info/WHEEL
PyANSI-1.2.0.dist-info/top_level.txt
PyANSI-1.2.0.dist-info/RECORD
