Metadata-Version: 2.1
Name: PyANSI
Version: 1.2.0
Summary: Easy ANSI control
Home-page: https://github.com/oliverjane/PyANSI
Author: Oliver Jane
License: UNKNOWN
Project-URL: Bug Tracker, https://github.com/oliverjane/PyANSI/issues
Platform: UNKNOWN
Classifier: Development Status :: 4 - Beta
Classifier: License :: OSI Approved :: GNU General Public License v3 (GPLv3)
Classifier: Operating System :: OS Independent
Classifier: Programming Language :: Python :: 2
Classifier: Programming Language :: Python :: 3
License-File: LICENSE
